gcovr/__init__.py
gcovr/__main__.py
gcovr/configuration.py
gcovr/decision_analysis.py
gcovr/exceptions.py
gcovr/filter.py
gcovr/logging.py
gcovr/options.py
gcovr/py.typed
gcovr/timestamps.py
gcovr/utils.py
gcovr/version.py
gcovr/data_model/__init__.py
gcovr/data_model/container.py
gcovr/data_model/coverage.py
gcovr/data_model/coverage_dict.py
gcovr/data_model/merging.py
gcovr/data_model/stats.py
gcovr/data_model/version.py
gcovr/exclusions/__init__.py
gcovr/exclusions/markers.py
gcovr/exclusions/noncode.py
gcovr/exclusions/utils.py
gcovr/formats/__init__.py
gcovr/formats/base.py
gcovr/formats/clover/__init__.py
gcovr/formats/clover/write.py
gcovr/formats/cobertura/__init__.py
gcovr/formats/cobertura/read.py
gcovr/formats/cobertura/write.py
gcovr/formats/coveralls/__init__.py
gcovr/formats/coveralls/write.py
gcovr/formats/csv/__init__.py
gcovr/formats/csv/write.py
gcovr/formats/gcov/__init__.py
gcovr/formats/gcov/read.py
gcovr/formats/gcov/workers.py
gcovr/formats/gcov/parser/__init__.py
gcovr/formats/gcov/parser/common.py
gcovr/formats/gcov/parser/json.py
gcovr/formats/gcov/parser/text.py
gcovr/formats/html/__init__.py
gcovr/formats/html/write.py
gcovr/formats/html/common/base.html
gcovr/formats/html/common/functions_page.content.html
gcovr/formats/html/common/gcovr.js
gcovr/formats/html/common/single_page.html
gcovr/formats/html/common/source_page.navigation.html
gcovr/formats/html/common/style.common.css
gcovr/formats/html/default/directory_page.content.html
gcovr/formats/html/default/directory_page.html
gcovr/formats/html/default/directory_page.navigation.html
gcovr/formats/html/default/directory_page.summary.html
gcovr/formats/html/default/functions_page.html
gcovr/formats/html/default/functions_page.summary.html
gcovr/formats/html/default/pygments.blue
gcovr/formats/html/default/pygments.green
gcovr/formats/html/default/source_page.content.html
gcovr/formats/html/default/source_page.html
gcovr/formats/html/default/source_page.summary.html
gcovr-8.5.dist-info/METADATA
gcovr-8.5.dist-info/WHEEL
gcovr-8.5.dist-info/entry_points.txt
gcovr-8.5.dist-info/licenses/LICENSE.txt
gcovr-8.5.dist-info/RECORD
