Metadata-Version: 2.4
Name: gcovr
Version: 8.5
Summary: Generate C/C++ code coverage reports with gcov
Project-URL: Documentation, https://gcovr.com
Project-URL: Github, https://github.com/gcovr/gcovr
Project-URL: Issues, https://github.com/gcovr/gcovr/issues
Author-email: Lukas Atkinson <opensource@lukasatkinson.de>, Michael Förderer <michael.foerderer@gmx.de>
License-Expression: BSD-3-Clause
License-File: LICENSE.txt
Keywords: Cobertura,Jenkins,coverage,gcc,gcov,lcov
Classifier: Development Status :: 5 - Production/Stable
Classifier: Environment :: Console
Classifier: Intended Audience :: Developers
Classifier: Intended Audience :: Science/Research
Classifier: License :: OSI Approved :: BSD License
Classifier: Natural Language :: English
Classifier: Operating System :: MacOS :: MacOS X
Classifier: Operating System :: Microsoft :: Windows
Classifier: Operating System :: POSIX
Classifier: Operating System :: Unix
Classifier: Programming Language :: Python
Classifier: Programming Language :: Python :: 3
Classifier: Programming Language :: Python :: 3.9
Classifier: Programming Language :: Python :: 3.10
Classifier: Programming Language :: Python :: 3.11
Classifier: Programming Language :: Python :: 3.12
Classifier: Programming Language :: Python :: 3.13
Classifier: Topic :: Software Development
Classifier: Topic :: Software Development :: Quality Assurance
Classifier: Topic :: Software Development :: Testing
Classifier: Topic :: Utilities
Requires-Python: >=3.9
Requires-Dist: colorlog
Requires-Dist: jinja2
Requires-Dist: lxml
Requires-Dist: pygments>=2.13.0
Requires-Dist: tomli>=1.1.0; python_version < '3.11'
Provides-Extra: dev
Requires-Dist: bandit[toml]; extra == 'dev'
Requires-Dist: build; extra == 'dev'
Requires-Dist: cmake; extra == 'dev'
Requires-Dist: coverage; extra == 'dev'
Requires-Dist: mypy; extra == 'dev'
Requires-Dist: nox; extra == 'dev'
Requires-Dist: pre-commit; extra == 'dev'
Requires-Dist: pygments==2.19.2; extra == 'dev'
Requires-Dist: pyinstaller~=6.16.0; extra == 'dev'
Requires-Dist: pylint<4.0.0; extra == 'dev'
Requires-Dist: pytest; extra == 'dev'
Requires-Dist: pytest-check; extra == 'dev'
Requires-Dist: pytest-cov; extra == 'dev'
Requires-Dist: pytest-env; extra == 'dev'
Requires-Dist: pytest-timeout; extra == 'dev'
Requires-Dist: pytest-xdist; extra == 'dev'
Requires-Dist: pywin32; (sys_platform == 'win32') and extra == 'dev'
Requires-Dist: requests; extra == 'dev'
Requires-Dist: ruff~=0.13.2; extra == 'dev'
Requires-Dist: tomli>=1.1.0; (python_version < '3.11') and extra == 'dev'
Requires-Dist: twine; extra == 'dev'
Requires-Dist: wheel; extra == 'dev'
Requires-Dist: yamllint; extra == 'dev'
Requires-Dist: yaxmldiff; extra == 'dev'
